aiidalab_eln/__init__.py
aiidalab_eln/base_connector.py
aiidalab_eln/version.py
aiidalab_eln/cheminfo/__init__.py
aiidalab_eln/cheminfo/exporter.py
aiidalab_eln/cheminfo/importer.py
aiidalab_eln-0.1.3.dist-info/LICENSE
aiidalab_eln-0.1.3.dist-info/METADATA
aiidalab_eln-0.1.3.dist-info/WHEEL
aiidalab_eln-0.1.3.dist-info/top_level.txt
aiidalab_eln-0.1.3.dist-info/RECORD
