Metadata-Version: 2.1
Name: aiidalab_eln
Version: 0.1.3
Summary: Package that integrates AiiDAlab with Electronic Laboratory Notebooks.
Home-page: https://github.com/aiidalab/aiidalab-eln
Author: The AiiDAlab team
Author-email: aiidalab@materialscloud.org
License: MIT
Classifier: Framework :: AiiDA
Classifier: License :: OSI Approved :: MIT License
Classifier: Operating System :: MacOS :: MacOS X
Classifier: Operating System :: POSIX :: Linux
Classifier: Programming Language :: Python :: 3
Classifier: Programming Language :: Python :: 3 :: Only
Requires-Python: >=3.8
License-File: LICENSE
Requires-Dist: aiida-core <3,>=1.1.0
Requires-Dist: ase
Requires-Dist: cheminfopy >=0.6.0
Requires-Dist: ipywidgets
Requires-Dist: pytojcamp
Requires-Dist: requests
Provides-Extra: dev
Requires-Dist: bumpver ==2021.1114 ; extra == 'dev'
Requires-Dist: pre-commit ==2.10.1 ; extra == 'dev'
